chat_archive/__init__.py
chat_archive/cli.py
chat_archive/database.py
chat_archive/emoji.py
chat_archive/models.py
chat_archive/profiling.py
chat_archive/tests.py
chat_archive/utils.py
chat_archive/alembic/env.py
chat_archive/alembic/script.py.mako
chat_archive/alembic/versions/96ac1e0e5dac_initial_revision.py
chat_archive/backends/__init__.py
chat_archive/backends/gtalk.py
chat_archive/backends/hangouts.py
chat_archive/backends/slack.py
chat_archive/backends/telegram.py
chat_archive/html/__init__.py
chat_archive/html/keywords.py
chat_archive/html/redirects.py
chat_archive-4.0.3.dist-info/LICENSE.txt
chat_archive-4.0.3.dist-info/METADATA
chat_archive-4.0.3.dist-info/WHEEL
chat_archive-4.0.3.dist-info/entry_points.txt
chat_archive-4.0.3.dist-info/top_level.txt
chat_archive-4.0.3.dist-info/RECORD
