Metadata-Version: 2.1
Name: chat-archive
Version: 4.0.3
Summary: Easy to use offline chat archive
Home-page: https://github.com/xolox/python-chat-archive
Author: Peter Odding
Author-email: peter@peterodding.com
License: MIT
Platform: UNKNOWN
Classifier: Development Status :: 4 - Beta
Classifier: Intended Audience :: Developers
Classifier: Intended Audience :: Information Technology
Classifier: Intended Audience :: System Administrators
Classifier: License :: OSI Approved :: MIT License
Classifier: Programming Language :: Python
Classifier: Programming Language :: Python :: 3
Classifier: Programming Language :: Python :: 3.5
Classifier: Programming Language :: Python :: 3.6
Classifier: Topic :: Software Development
Classifier: Topic :: Software Development :: Libraries
Classifier: Topic :: Software Development :: Libraries :: Python Modules
Classifier: Topic :: Text Processing
Classifier: Topic :: Text Processing :: Indexing
Requires-Dist: alembic (>=0.8.6)
Requires-Dist: coloredlogs (>=10.0)
Requires-Dist: emoji (>=0.5.0)
Requires-Dist: hangups (>=0.4.6)
Requires-Dist: humanfriendly (>=4.16.1)
Requires-Dist: property-manager (>=2.3.1)
Requires-Dist: qpass (>=2.2.1)
Requires-Dist: slacker (>=0.9.65)
Requires-Dist: sqlalchemy (>=1.2.8)
Requires-Dist: telethon (>=1.0.2)
Requires-Dist: update-dotdee (>=5.0)
Requires-Dist: verboselogs (>=1.7)
